torch_pconv/__init__.py
torch_pconv/pconv.py
torch_pconv-0.1.1.dist-info/LICENCE.txt
torch_pconv-0.1.1.dist-info/METADATA
torch_pconv-0.1.1.dist-info/WHEEL
torch_pconv-0.1.1.dist-info/top_level.txt
torch_pconv-0.1.1.dist-info/RECORD
