Metadata-Version: 2.1
Name: torch-pconv
Version: 0.1.1
Summary: Faster and more memory efficient implementation of the Partial Convolution 2D layer in PyTorch equivalent to the standard NVidia implem.
Home-page: https://github.com/DesignStripe/torch_pconv
Author: Samuel Prevost
Author-email: samuel.prevost@pm.me
License: BSD
Platform: UNKNOWN
Classifier: License :: OSI Approved :: BSD License
Classifier: Programming Language :: Python :: 3
Classifier: Programming Language :: Python :: 3.8
Requires-Dist: torch
Requires-Dist: tensor-type
Requires-Dist: pshape
